{
  "providers": [
    { "id": "bankofamerica", "files": ["bankofamerica/transfer_zelle.json"] },
    { "id": "cashapp", "files": ["cashapp/transfer_cashapp.json"] },
    { "id": "chase", "files": ["chase/transfer_zelle.json"] },
    { "id": "citi", "files": ["citi/transfer_zelle.json"] },
    { "id": "idfc", "files": ["idfc/transfer_idfc.json"] },
    { "id": "luxon", "files": ["luxon/transfer_luxon.json"] },
    { "id": "mercadopago", "files": ["mercadopago/transfer_mercadopago.json"] },
    { "id": "monzo", "files": ["monzo/transfer_monzo.json"] },
    { "id": "paypal", "files": ["paypal/transfer_paypal.json"] },
    { "id": "revolut", "files": ["revolut/transfer_revolut.json"] },
    { "id": "royalbankcanada", "files": ["royalbankcanada/transfer_interac.json"] },
    { "id": "usbank", "files": ["usbank/transfer_zelle.json"] },
    { "id": "venmo", "files": ["venmo/transfer_venmo.json"] },
    { "id": "wise", "files": ["wise/transfer_wise.json"] },
    { "id": "n26", "files": ["n26/transfer_n26.json"] }
  ]
}
